Workbook

Sheet Sheet1
A1: Virtus Health | F1: 45949
F2: Calculated weeks APA
A3: Employee ID | B3: Entity List | C3: LSL Instrument | D3: Status | E3: LSL start date | F3: Entitlement (Weeks) | G3: Micropay balance in weeks | H3: Variance | I3: Comment
A4: AU21005 | B4: VIC-TAS | C4: MIVFS2022 | D4: Full time | E4: =VLOOKUP(A4,'[1]Virtus SAMPLE PositionHistorySa'!$A:$L,12,0) | F4: 54.11 | G4: =VLOOKUP(A4,Sheet3!A:K,10,0)/38 | H4: =F4-G4
A5: 60125 | B5: NSW-QLD | C5: QN2025 | D5: Full time | E5: =VLOOKUP(A5,'[1]Virtus SAMPLE PositionHistorySa'!$A:$L,12,0) | F5: 10.81 | G5: =VLOOKUP(A5,Sheet3!A:K,10,0)/38 | H5: =F5-G5
A6: 90145 | B6: NSW-QLD | C6: IVFS2023 | D6: Part time | E6: =VLOOKUP(A6,'[1]Virtus SAMPLE PositionHistorySa'!$A:$L,12,0) | F6: 25.10
A7: 80108 | B7: NSW-QLD | C7: QS2024 | D7: Part time | E7: =VLOOKUP(A7,'[1]Virtus SAMPLE PositionHistorySa'!$A:$L,12,0) | F7: 20.90
A8: 20082 | B8: NSW-QLD | C8: NSW | D8: Full time | E8: =VLOOKUP(A8,'[1]Virtus SAMPLE PositionHistorySa'!$A:$L,12,0) | F8: 15.28 | G8: =VLOOKUP(A8,Sheet3!A:K,10,0)/38 | H8: =F8-G8
A9: 80026 | B9: NSW-QLD | C9: QLD | D9: Part time | E9: =VLOOKUP(A9,'[1]Virtus SAMPLE PositionHistorySa'!$A:$L,12,0) | F9: 2.25
A10: AU21025 | B10: VIC-TAS | C10: MIVFS2022 | D10: Full time | E10: =VLOOKUP(A10,'[1]Virtus SAMPLE PositionHistorySa'!$A:$L,12,0) | F10: 41.69 | G10: =VLOOKUP(A10,Sheet3!A:K,10,0)/38 | H10: =F10-G10
A11: 60118 | B11: NSW-QLD | C11: QN2025 | D11: Part time | E11: =VLOOKUP(A11,'[1]Virtus SAMPLE PositionHistorySa'!$A:$L,12,0) | F11: 25.14
A12: 60018 | B12: NSW-QLD | C12: QN2025 | D12: Part time | E12: =VLOOKUP(A12,'[1]Virtus SAMPLE PositionHistorySa'!$A:$L,12,0) | F12: 23.33
A13: 80042 | B13: NSW-QLD | C13: QS2024 | D13: Full time | E13: =VLOOKUP(A13,'[1]Virtus SAMPLE PositionHistorySa'!$A:$L,12,0) | F13: 20.71 | G13: =VLOOKUP(A13,Sheet3!A:K,10,0)/38 | H13: =F13-G13
A14: 20063 | B14: NSW-QLD | C14: IVFS2023 | D14: Part time | E14: =VLOOKUP(A14,'[1]Virtus SAMPLE PositionHistorySa'!$A:$L,12,0) | F14: 0.00
A15: AU21035 | B15: VIC-TAS | C15: MIVFS2022 | D15: Full time | E15: =VLOOKUP(A15,'[1]Virtus SAMPLE PositionHistorySa'!$A:$L,12,0) | F15: 40.66 | G15: =VLOOKUP(A15,Sheet3!A:K,10,0)/38 | H15: =F15-G15
A16: 20156 | B16: NSW-QLD | C16: IVFN2021 | D16: Full time | E16: =VLOOKUP(A16,'[1]Virtus SAMPLE PositionHistorySa'!$A:$L,12,0) | F16: 20.32 | G16: =VLOOKUP(A16,Sheet3!A:K,10,0)/38 | H16: =F16-G16
A17: 19802 | B17: NSW-QLD | C17: IVFN2021 | D17: Full time | E17: =VLOOKUP(A17,'[1]Virtus SAMPLE PositionHistorySa'!$A:$L,12,0) | F17: 18.67 | G17: =VLOOKUP(A17,Sheet3!A:K,10,0)/38 | H17: =F17-G17
A18: 20146 | B18: NSW-QLD | C18: NSW | D18: Full time | E18: =VLOOKUP(A18,'[1]Virtus SAMPLE PositionHistorySa'!$A:$L,12,0) | F18: 17.64 | G18: =VLOOKUP(A18,Sheet3!A:K,10,0)/38 | H18: =F18-G18
A19: 20172 | B19: NSW-QLD | C19: IVFN2021 | D19: Part time | E19: =VLOOKUP(A19,'[1]Virtus SAMPLE PositionHistorySa'!$A:$L,12,0) | F19: 6.89
A20: 60112 | B20: NSW-QLD | C20: QN2025 | D20: Casual | E20: =VLOOKUP(A20,'[1]Virtus SAMPLE PositionHistorySa'!$A:$L,12,0) | F20: 26.05
A21: 80031 | B21: NSW-QLD | C21: QN2025 | D21: Part time | E21: =VLOOKUP(A21,'[1]Virtus SAMPLE PositionHistorySa'!$A:$L,12,0) | F21: 5.40
A22: 20080 | B22: NSW-QLD | C22: IVFS2023 | D22: Part time | E22: =VLOOKUP(A22,'[1]Virtus SAMPLE PositionHistorySa'!$A:$L,12,0) | F22: 11.80
A23: 20091 | B23: NSW-QLD | C23: IVFS2023 | D23: Part time | E23: =VLOOKUP(A23,'[1]Virtus SAMPLE PositionHistorySa'!$A:$L,12,0) | F23: 8.22
A24: 20056 | B24: NSW-QLD | C24: IVFS2023 | D24: Part time | E24: =VLOOKUP(A24,'[1]Virtus SAMPLE PositionHistorySa'!$A:$L,12,0) | F24: 0.00
A25: 80434 | B25: NSW-QLD | C25: QN2025 | D25: Part time | E25: =VLOOKUP(A25,'[1]Virtus SAMPLE PositionHistorySa'!$A:$L,12,0) | F25: 22.11
A26: 40007 | B26: NSW-QLD | C26: IVFN2021 | D26: Part time | E26: =VLOOKUP(A26,'[1]Virtus SAMPLE PositionHistorySa'!$A:$L,12,0) | F26: 1.62
A27: 20123 | B27: NSW-QLD | C27: IVFS2023 | D27: Part time | E27: =VLOOKUP(A27,'[1]Virtus SAMPLE PositionHistorySa'!$A:$L,12,0) | F27: 12.15
A28: 153 | B28: VIC-TAS | C28: MIVFN2023 | D28: Part time | E28: =VLOOKUP(A28,'[1]Virtus SAMPLE PositionHistorySa'!$A:$L,12,0) | F28: 32.55
A29: 165 | B29: VIC-TAS | C29: MIVFS2022 | D29: Full time | E29: =VLOOKUP(A29,'[1]Virtus SAMPLE PositionHistorySa'!$A:$L,12,0) | F29: 32.11 | G29: =VLOOKUP(A29,Sheet3!A:K,10,0)/38 | H29: =F29-G29
A30: 198 | B30: VIC-TAS | C30: MIVFS2022 | D30: Part time | E30: =VLOOKUP(A30,'[1]Virtus SAMPLE PositionHistorySa'!$A:$L,12,0) | F30: 30.96
A31: 50027 | B31: NSW-QLD | C31: IVFN2021 | D31: Part time | E31: =VLOOKUP(A31,'[1]Virtus SAMPLE PositionHistorySa'!$A:$L,12,0) | F31: 15.69
A32: 214 | B32: VIC-TAS | C32: MIVFS2022 | D32: Full time | E32: =VLOOKUP(A32,'[1]Virtus SAMPLE PositionHistorySa'!$A:$L,12,0) | F32: 30.13 | G32: =VLOOKUP(A32,Sheet3!A:K,10,0)/38 | H32: =F32-G32
A33: 39 | B33: VIC-TAS | C33: TIVF2024 | D33: Part time | E33: =VLOOKUP(A33,'[1]Virtus SAMPLE PositionHistorySa'!$A:$L,12,0) | F33: 15.13
A34: 60129 | B34: NSW-QLD | C34: QN2025 | D34: Part time | E34: =VLOOKUP(A34,'[1]Virtus SAMPLE PositionHistorySa'!$A:$L,12,0) | F34: 0.00
A35: 20175 | B35: NSW-QLD | C35: IVFN2021 | D35: Part time | E35: =VLOOKUP(A35,'[1]Virtus SAMPLE PositionHistorySa'!$A:$L,12,0) | F35: 0.00
A36: 20033 | B36: NSW-QLD | C36: IVFS2023 | D36: Full time | E36: =VLOOKUP(A36,'[1]Virtus SAMPLE PositionHistorySa'!$A:$L,12,0) | F36: 3.05 | G36: =VLOOKUP(A36,Sheet3!A:K,10,0)/38 | H36: =F36-G36
A37: 80105 | B37: NSW-QLD | C37: QS2024 | D37: Full time | E37: =VLOOKUP(A37,'[1]Virtus SAMPLE PositionHistorySa'!$A:$L,12,0) | F37: 5.89 | G37: =VLOOKUP(A37,Sheet3!A:K,10,0)/38 | H37: =F37-G37
A38: 20752 | B38: NSW-QLD | C38: QLD | D38: =VLOOKUP(A38,Sheet3!A:E,5,0) | E38: =VLOOKUP(A38,'[1]Virtus SAMPLE PositionHistorySa'!$A:$L,12,0) | F38: 13.91
A39: 20016 | B39: NSW-QLD | C39: IVFT2024 | D39: Part time | E39: =VLOOKUP(A39,'[1]Virtus SAMPLE PositionHistorySa'!$A:$L,12,0) | F39: 2.26
A40: 318 | B40: VIC-TAS | C40: MIVFS2022 | D40: Part time | E40: =VLOOKUP(A40,'[1]Virtus SAMPLE PositionHistorySa'!$A:$L,12,0) | F40: 27.67
A41: 50009 | B41: NSW-QLD | C41: IVFS2023 | D41: Full time | E41: =VLOOKUP(A41,'[1]Virtus SAMPLE PositionHistorySa'!$A:$L,12,0) | F41: 11.05 | G41: =VLOOKUP(A41,Sheet3!A:K,10,0)/38 | H41: =F41-G41
A42: 20176 | B42: NSW-QLD | C42: IVFN2021 | D42: Part time | E42: =VLOOKUP(A42,'[1]Virtus SAMPLE PositionHistorySa'!$A:$L,12,0) | F42: 9.78
A43: 20145 | B43: NSW-QLD | C43: IVFN2021 | D43: Part time | E43: =VLOOKUP(A43,'[1]Virtus SAMPLE PositionHistorySa'!$A:$L,12,0) | F43: 14.27
A44: 20186 | B44: NSW-QLD | C44: IVFC2022 | D44: Part time | E44: =VLOOKUP(A44,'[1]Virtus SAMPLE PositionHistorySa'!$A:$L,12,0) | F44: 10.76
A45: 30021 | B45: NSW-QLD | C45: IVFN2021 | D45: Part time | E45: =VLOOKUP(A45,'[1]Virtus SAMPLE PositionHistorySa'!$A:$L,12,0) | F45: 1.91
A46: 80103 | B46: NSW-QLD | C46: QS2024 | D46: Full time | E46: =VLOOKUP(A46,'[1]Virtus SAMPLE PositionHistorySa'!$A:$L,12,0) | F46: 20.51 | G46: =VLOOKUP(A46,Sheet3!A:K,10,0)/38 | H46: =F46-G46
A47: 19801 | B47: NSW-QLD | C47: IVFT2024 | D47: Full time | E47: =VLOOKUP(A47,'[1]Virtus SAMPLE PositionHistorySa'!$A:$L,12,0) | F47: 7.88 | G47: =VLOOKUP(A47,Sheet3!A:K,10,0)/38 | H47: =F47-G47
A48: 60024 | B48: NSW-QLD | C48: QN2025 | D48: Part time | E48: =VLOOKUP(A48,'[1]Virtus SAMPLE PositionHistorySa'!$A:$L,12,0) | F48: 12.24
A49: 19811 | B49: NSW-QLD | C49: IVFS2023 | D49: Full time | E49: =VLOOKUP(A49,'[1]Virtus SAMPLE PositionHistorySa'!$A:$L,12,0) | F49: 10.89 | G49: =VLOOKUP(A49,Sheet3!A:K,10,0)/38 | H49: =F49-G49
A50: 80293 | B50: NSW-QLD | C50: QN2025 | D50: Casual | E50: =VLOOKUP(A50,'[1]Virtus SAMPLE PositionHistorySa'!$A:$L,12,0) | F50: 20.53
A51: 32 | B51: VIC-TAS | C51: TIVF2024 | D51: Full time | E51: =VLOOKUP(A51,'[1]Virtus SAMPLE PositionHistorySa'!$A:$L,12,0) | F51: 13.53 | G51: =VLOOKUP(A51,Sheet3!A:K,10,0)/38 | H51: =F51-G51
A52: 50003 | B52: NSW-QLD | C52: IVFS2023 | D52: Part time | E52: =VLOOKUP(A52,'[1]Virtus SAMPLE PositionHistorySa'!$A:$L,12,0) | F52: 0.00
A53: 80110 | B53: NSW-QLD | C53: QS2024 | D53: Part time | E53: =VLOOKUP(A53,'[1]Virtus SAMPLE PositionHistorySa'!$A:$L,12,0) | F53: 19.85
A54: 20250 | B54: NSW-QLD | C54: NSW | D54: Full time | E54: =VLOOKUP(A54,'[1]Virtus SAMPLE PositionHistorySa'!$A:$L,12,0) | F54: 8.52 | G54: =VLOOKUP(A54,Sheet3!A:K,10,0)/38 | H54: =F54-G54
A55: 20236 | B55: NSW-QLD | C55: IVFC2022 | D55: Part time | E55: =VLOOKUP(A55,'[1]Virtus SAMPLE PositionHistorySa'!$A:$L,12,0) | F55: 2.61
A56: 40036 | B56: NSW-QLD | C56: IVFS2023 | D56: Full time | E56: =VLOOKUP(A56,'[1]Virtus SAMPLE PositionHistorySa'!$A:$L,12,0) | F56: 12.03 | G56: =VLOOKUP(A56,Sheet3!A:K,10,0)/38 | H56: =F56-G56
A57: 80122 | B57: NSW-QLD | C57: QS2024 | D57: Part time | E57: =VLOOKUP(A57,'[1]Virtus SAMPLE PositionHistorySa'!$A:$L,12,0) | F57: 18.80
A58: 368 | B58: VIC-TAS | C58: MIVFS2022 | D58: Full time | E58: =VLOOKUP(A58,'[1]Virtus SAMPLE PositionHistorySa'!$A:$L,12,0) | F58: 25.64 | G58: =VLOOKUP(A58,Sheet3!A:K,10,0)/38 | H58: =F58-G58
A59: 80117 | B59: NSW-QLD | C59: QS2024 | D59: Part time | E59: =VLOOKUP(A59,'[1]Virtus SAMPLE PositionHistorySa'!$A:$L,12,0) | F59: 18.91
A60: 20263 | B60: NSW-QLD | C60: NSW | D60: Full time | E60: =VLOOKUP(A60,'[1]Virtus SAMPLE PositionHistorySa'!$A:$L,12,0) | F60: 0.00 | G60: =VLOOKUP(A60,Sheet3!A:K,10,0)/38 | H60: =F60-G60
A61: 100018 | B61: NSW-QLD | C61: ACT | D61: Full time | E61: =VLOOKUP(A61,'[1]Virtus SAMPLE PositionHistorySa'!$A:$L,12,0) | F61: 12.02 | G61: =VLOOKUP(A61,Sheet3!A:K,10,0)/38 | H61: =F61-G61
A62: 442 | B62: VIC-TAS | C62: MIVFN2023 | D62: Part time | E62: =VLOOKUP(A62,'[1]Virtus SAMPLE PositionHistorySa'!$A:$L,12,0) | F62: 24.61
A63: 406 | B63: VIC-TAS | C63: MIVFS2022 | D63: Full time | E63: =VLOOKUP(A63,'[1]Virtus SAMPLE PositionHistorySa'!$A:$L,12,0) | F63: 25.18 | G63: =VLOOKUP(A63,Sheet3!A:K,10,0)/38 | H63: =F63-G63
A64: 20248 | B64: NSW-QLD | C64: IVFS2023 | D64: Part time | E64: =VLOOKUP(A64,'[1]Virtus SAMPLE PositionHistorySa'!$A:$L,12,0) | F64: 12.37
A65: 455 | B65: VIC-TAS | C65: MIVFS2022 | D65: Full time | E65: =VLOOKUP(A65,'[1]Virtus SAMPLE PositionHistorySa'!$A:$L,12,0) | F65: 24.45 | G65: =VLOOKUP(A65,Sheet3!A:K,10,0)/38 | H65: =F65-G65
A66: 40040 | B66: NSW-QLD | C66: IVFN2021 | D66: Full time | E66: =VLOOKUP(A66,'[1]Virtus SAMPLE PositionHistorySa'!$A:$L,12,0) | F66: 8.82 | G66: =VLOOKUP(A66,Sheet3!A:K,10,0)/38 | H66: =F66-G66
A67: 20281 | B67: NSW-QLD | C67: IVFN2021 | D67: Part time | E67: =VLOOKUP(A67,'[1]Virtus SAMPLE PositionHistorySa'!$A:$L,12,0) | F67: 11.82
A68: 30101 | B68: NSW-QLD | C68: IVFN2021 | D68: Casual | E68: =VLOOKUP(A68,'[1]Virtus SAMPLE PositionHistorySa'!$A:$L,12,0) | F68: 11.45
A69: 20308 | B69: NSW-QLD | C69: IVFT2024 | D69: Full time | E69: =VLOOKUP(A69,'[1]Virtus SAMPLE PositionHistorySa'!$A:$L,12,0) | F69: 5.21 | G69: =VLOOKUP(A69,Sheet3!A:K,10,0)/38 | H69: =F69-G69
A70: 700 | B70: VIC-TAS | C70: MIVFS2022 | D70: Part time | E70: =VLOOKUP(A70,'[1]Virtus SAMPLE PositionHistorySa'!$A:$L,12,0) | F70: 22.62
A71: 512 | B71: VIC-TAS | C71: MIVFS2022 | D71: Full time | E71: =VLOOKUP(A71,'[1]Virtus SAMPLE PositionHistorySa'!$A:$L,12,0) | F71: 23.48 | G71: =VLOOKUP(A71,Sheet3!A:K,10,0)/38 | H71: =F71-G71
A72: 20872 | B72: NSW-QLD | C72: VIC | D72: Full time | E72: =VLOOKUP(A72,'[1]Virtus SAMPLE PositionHistorySa'!$A:$L,12,0) | F72: 1.53 | G72: =VLOOKUP(A72,Sheet3!A:K,10,0)/38 | H72: =F72-G72
A73: 20322 | B73: NSW-QLD | C73: IVFT2024 | D73: Full time | E73: =VLOOKUP(A73,'[1]Virtus SAMPLE PositionHistorySa'!$A:$L,12,0) | F73: 1.15 | G73: =VLOOKUP(A73,Sheet3!A:K,10,0)/38 | H73: =F73-G73
A74: 20292 | B74: NSW-QLD | C74: IVFT2024 | D74: Part time | E74: =VLOOKUP(A74,'[1]Virtus SAMPLE PositionHistorySa'!$A:$L,12,0) | F74: 3.59
A75: 80061 | B75: NSW-QLD | C75: QS2024 | D75: Part time | E75: =VLOOKUP(A75,'[1]Virtus SAMPLE PositionHistorySa'!$A:$L,12,0) | F75: 6.81
A76: 80071 | B76: NSW-QLD | C76: IVFS2023 | D76: Part time | E76: =VLOOKUP(A76,'[1]Virtus SAMPLE PositionHistorySa'!$A:$L,12,0) | F76: 4.81
A77: 20276 | B77: NSW-QLD | C77: IVFC2022 | D77: Part time | E77: =VLOOKUP(A77,'[1]Virtus SAMPLE PositionHistorySa'!$A:$L,12,0) | F77: 1.78
A78: 80046 | B78: NSW-QLD | C78: QS2024 | D78: Part time | E78: =VLOOKUP(A78,'[1]Virtus SAMPLE PositionHistorySa'!$A:$L,12,0) | F78: 2.05
A79: 20324 | B79: NSW-QLD | C79: IVFN2021 | D79: Part time | E79: =VLOOKUP(A79,'[1]Virtus SAMPLE PositionHistorySa'!$A:$L,12,0) | F79: 10.11
A80: AU22655 | B80: VIC-TAS | C80: MIVFS2022 | D80: Part time | E80: =VLOOKUP(A80,'[1]Virtus SAMPLE PositionHistorySa'!$A:$L,12,0) | F80: 20.88
A81: 20330 | B81: NSW-QLD | C81: IVFS2023 | D81: Full time | E81: =VLOOKUP(A81,'[1]Virtus SAMPLE PositionHistorySa'!$A:$L,12,0) | F81: 9.94 | G81: =VLOOKUP(A81,Sheet3!A:K,10,0)/38 | H81: =F81-G81
A82: 40056 | B82: NSW-QLD | C82: IVFS2023 | D82: Casual | E82: =VLOOKUP(A82,'[1]Virtus SAMPLE PositionHistorySa'!$A:$L,12,0) | F82: 3.91
A83: 80125 | B83: NSW-QLD | C83: QS2024 | D83: Full time | E83: =VLOOKUP(A83,'[1]Virtus SAMPLE PositionHistorySa'!$A:$L,12,0) | F83: 10.50 | G83: =VLOOKUP(A83,Sheet3!A:K,10,0)/38 | H83: =F83-G83
A84: 20341 | B84: NSW-QLD | C84: NSW | D84: Full time | E84: =VLOOKUP(A84,'[1]Virtus SAMPLE PositionHistorySa'!$A:$L,12,0) | F84: 8.93 | G84: =VLOOKUP(A84,Sheet3!A:K,10,0)/38 | H84: =F84-G84
A85: 786 | B85: VIC-TAS | C85: MIVFN2023 | D85: Part time | E85: =VLOOKUP(A85,'[1]Virtus SAMPLE PositionHistorySa'!$A:$L,12,0) | F85: 20.69
A86: 60182 | B86: NSW-QLD | C86: IVFS2023 | D86: Part time | E86: =VLOOKUP(A86,'[1]Virtus SAMPLE PositionHistorySa'!$A:$L,12,0) | F86: 5.39
A87: 796 | B87: VIC-TAS | C87: MIVFS2022 | D87: Part time | E87: =VLOOKUP(A87,'[1]Virtus SAMPLE PositionHistorySa'!$A:$L,12,0) | F87: 20.43
A88: 869 | B88: VIC-TAS | C88: MIVFS2022 | D88: Part time | E88: =VLOOKUP(A88,'[1]Virtus SAMPLE PositionHistorySa'!$A:$L,12,0) | F88: 19.12
A89: 846 | B89: VIC-TAS | C89: MIVFS2022 | D89: Full time | E89: =VLOOKUP(A89,'[1]Virtus SAMPLE PositionHistorySa'!$A:$L,12,0) | F89: 19.55 | G89: =VLOOKUP(A89,Sheet3!A:K,10,0)/38 | H89: =F89-G89
A90: 20413 | B90: NSW-QLD | C90: IVFN2021 | D90: Full time | E90: =VLOOKUP(A90,'[1]Virtus SAMPLE PositionHistorySa'!$A:$L,12,0) | F90: 9.63 | G90: =VLOOKUP(A90,Sheet3!A:K,10,0)/38 | H90: =F90-G90
A91: 838 | B91: VIC-TAS | C91: MIVFS2022 | D91: Full time | E91: =VLOOKUP(A91,'[1]Virtus SAMPLE PositionHistorySa'!$A:$L,12,0) | F91: 19.69 | G91: =VLOOKUP(A91,Sheet3!A:K,10,0)/38 | H91: =F91-G91
A92: 90022 | B92: NSW-QLD | C92: IVFS2023 | D92: Full time | E92: =VLOOKUP(A92,'[1]Virtus SAMPLE PositionHistorySa'!$A:$L,12,0) | F92: 9.70 | G92: =VLOOKUP(A92,Sheet3!A:K,10,0)/38 | H92: =F92-G92
A93: 20404 | B93: NSW-QLD | C93: IVFT2024 | D93: Full time | E93: =VLOOKUP(A93,'[1]Virtus SAMPLE PositionHistorySa'!$A:$L,12,0) | F93: 0.96 | G93: =VLOOKUP(A93,Sheet3!A:K,10,0)/38 | H93: =F93-G93
A94: 19009 | B94: NSW-QLD | C94: VIC | D94: Full time | E94: =VLOOKUP(A94,'[1]Virtus SAMPLE PositionHistorySa'!$A:$L,12,0) | F94: 15.26 | G94: =VLOOKUP(A94,Sheet3!A:K,10,0)/38 | H94: =F94-G94 | I94: confirm start date
A95: 80139 | B95: NSW-QLD | C95: IVFS2023 | D95: Part time | E95: =VLOOKUP(A95,'[1]Virtus SAMPLE PositionHistorySa'!$A:$L,12,0) | F95: 8.06
A96: 80137 | B96: NSW-QLD | C96: QLD | D96: Full time | E96: =VLOOKUP(A96,'[1]Virtus SAMPLE PositionHistorySa'!$A:$L,12,0) | F96: 6.14 | G96: =VLOOKUP(A96,Sheet3!A:K,10,0)/38 | H96: =F96-G96
A97: 857 | B97: VIC-TAS | C97: MIVFS2022 | D97: Full time | E97: =VLOOKUP(A97,'[1]Virtus SAMPLE PositionHistorySa'!$A:$L,12,0) | F97: 19.39 | G97: =VLOOKUP(A97,Sheet3!A:K,10,0)/38 | H97: =F97-G97
A98: 913 | B98: VIC-TAS | C98: MIVFN2023 | D98: Full time | E98: =VLOOKUP(A98,'[1]Virtus SAMPLE PositionHistorySa'!$A:$L,12,0) | F98: 8.57 | G98: =VLOOKUP(A98,Sheet3!A:K,10,0)/38 | H98: =F98-G98
A99: 20428 | B99: NSW-QLD | C99: IVFN2021 | D99: Full time | E99: =VLOOKUP(A99,'[1]Virtus SAMPLE PositionHistorySa'!$A:$L,12,0) | F99: 4.97 | G99: =VLOOKUP(A99,Sheet3!A:K,10,0)/38 | H99: =F99-G99
A100: 20474 | B100: NSW-QLD | C100: IVFS2023 | D100: Full time | E100: =VLOOKUP(A100,'[1]Virtus SAMPLE PositionHistorySa'!$A:$L,12,0) | F100: 7.70 | G100: =VLOOKUP(A100,Sheet3!A:K,10,0)/38 | H100: =F100-G100
...

Sheet Sheet2
A1: Employee ID | B1: Employee DOB | C1: Cohort | D1: System | E1: Title | F1: Position Effective Date | G1: Position End Date | H1: LSL Instrument | I1: State | J1: Employment Status | K1: Commencement Date | L1: LSL Adjusted Start Date | M1: Termination Date | N1: Termination Reason | O1: Fixed Ordinary Weekly Hours
A2: 12 | C2: VIC-TAS | D2: Virtus Health | E2: Embryologist | F2: 8/22/2011 | H2: TIVF2024 | I2: TAS | J2: Part Time | K2: 8/22/2011 | L2: 8/22/2011 | O2: 22.5
A3: 20 | C3: VIC-TAS | D3: Virtus Health | E3: Registered Nurse | F3: 4/16/2012 | H3: TIVF2024 | I3: TAS | J3: Casual | K3: 4/16/2012 | L3: 4/16/2012 | O3: 38
A4: 23 | C4: VIC-TAS | D4: Virtus Health | E4: Scientific Director | F4: 1/15/2001 | H4: TAS | I4: TAS | J4: Full Time | K4: 1/15/2001 | L4: 1/15/2001 | O4: 37.5
A5: 32 | C5: VIC-TAS | D5: Virtus Health | E5: Embryologist | F5: 40424 | H5: TIVF2024 | I5: TAS | J5: Full Time | K5: 40424 | L5: 40424 | O5: 37.5
A6: 38 | C6: VIC-TAS | D6: Virtus Health | E6: Registered Nurse | F6: 4/17/2012 | H6: TIVF2024 | I6: TAS | J6: Part Time | K6: 4/17/2012 | L6: 4/17/2012 | O6: 15
A7: 39 | C7: VIC-TAS | D7: Virtus Health | E7: Registered Nurse | F7: 39604 | H7: TIVF2024 | I7: TAS | J7: Part Time | K7: 39604 | L7: 39604 | O7: 21.5
A8: 45 | C8: VIC-TAS | D8: Virtus Health | E8: Patient Liaison Administrator | F8: 2/16/2016 | H8: TIVF2024 | I8: TAS | J8: Part Time | K8: 2/16/2016 | L8: 2/16/2016 | O8: 27.5
A9: 56 | C9: VIC-TAS | D9: Virtus Health | E9: Associate Nurse Unit Manager | F9: 3/27/2017 | H9: TIVF2024 | I9: TAS | J9: Part Time | K9: 3/27/2017 | L9: 3/27/2017 | O9: 36
A10: 57 | C10: VIC-TAS | D10: Virtus Health | E10: Enrolled Nurse | F10: 43012 | H10: TIVF2024 | I10: TAS | J10: Part Time | K10: 43012 | L10: 43012 | O10: 24
A11: 76 | C11: VIC-TAS | D11: Virtus Health | E11: Registered Nurse | F11: 7/30/2018 | H11: TIVF2024 | I11: TAS | J11: Part Time | K11: 7/30/2018 | L11: 7/30/2018 | O11: 24
A12: 88 | C12: VIC-TAS | D12: Virtus Health | E12: Embryologist | F12: 43681 | H12: TIVF2024 | I12: TAS | J12: Part Time | K12: 43681 | L12: 43681 | O12: 30
A13: 92 | C13: VIC-TAS | D13: Virtus Health | E13: Patient Administration Services Team Leader | F13: 7/15/2019 | H13: TIVF2024 | I13: TAS | J13: Full Time | K13: 7/15/2019 | L13: 7/15/2019 | O13: 37.5
A14: 95 | C14: VIC-TAS | D14: Virtus Health | E14: Registered Nurse | F14: 9/16/2019 | H14: TIVF2024 | I14: TAS | J14: Part Time | K14: 9/16/2019 | L14: 9/16/2019 | O14: 32
A15: 97 | C15: VIC-TAS | D15: Virtus Health | E15: Registered Nurse | F15: 44106 | H15: TIVF2024 | I15: TAS | J15: Full Time | K15: 44106 | L15: 44106 | O15: 37.5
A16: 99 | C16: VIC-TAS | D16: Virtus Health | E16: Registered Nurse | F16: 44106 | H16: TIVF2024 | I16: TAS | J16: Part Time | K16: 44106 | L16: 44106 | O16: 26
A17: 103 | C17: VIC-TAS | D17: Virtus Health | E17: Donor Coordinator | F17: 3/24/2020 | H17: TIVF2024 | I17: TAS | J17: Part Time | K17: 3/24/2020 | L17: 3/24/2020 | O17: 30
A18: 105 | C18: VIC-TAS | D18: Virtus Health | E18: Enrolled Nurse | F18: 44048 | H18: TIVF2024 | I18: TAS | J18: Casual | K18: 44048 | L18: 44048 | O18: 38
A19: 107 | C19: VIC-TAS | D19: Virtus Health | E19: Registered Nurse | F19: 6/15/2020 | H19: TIVF2024 | I19: TAS | J19: Part Time | K19: 6/15/2020 | L19: 6/15/2020 | O19: 16
A20: 109 | C20: VIC-TAS | D20: Virtus Health | E20: Registered Nurse | F20: 44080 | H20: TIVF2024 | I20: TAS | J20: Casual | K20: 44080 | L20: 44080 | O20: 38
A21: 115 | C21: VIC-TAS | D21: Virtus Health | E21: CSSD Theatre Technician | F21: 7/20/2020 | H21: TIVF2024 | I21: TAS | J21: Casual | K21: 7/20/2020 | L21: 7/20/2020 | O21: 38
A22: 118 | C22: VIC-TAS | D22: Virtus Health | E22: Registered Nurse | F22: 44021 | H22: TIVF2024 | I22: TAS | J22: Part Time | K22: 44021 | L22: 44021 | O22: 8
A23: 119 | C23: VIC-TAS | D23: Virtus Health | E23: Director of Nursing | F23: 9/28/2020 | H23: TAS | I23: TAS | J23: Full Time | K23: 9/28/2020 | L23: 9/28/2020 | O23: 37.5
A24: 120 | C24: VIC-TAS | D24: Virtus Health | E24: Registered Nurse | F24: 43932 | H24: TIVF2024 | I24: TAS | J24: Part Time | K24: 43932 | L24: 43932 | O24: 20
A25: 124 | C25: VIC-TAS | D25: Virtus Health | E25: Embryologist | F25: 1/23/2006 | H25: MIVFS2022 | I25: VIC | J25: Part Time | K25: 1/23/2006 | L25: 1/23/2006 | O25: 32
A26: 125 | C26: VIC-TAS | D26: Virtus Health | E26: Registered Nurse | F26: 44199 | H26: TIVF2024 | I26: TAS | J26: Full Time | K26: 44199 | L26: 44199 | O26: 37.5
A27: 131 | C27: VIC-TAS | D27: Virtus Health | E27: Registered Nurse | F27: 44204 | H27: TIVF2024 | I27: TAS | J27: Part Time | K27: 44204 | L27: 44204 | O27: 28
A28: 136 | C28: VIC-TAS | D28: Virtus Health | E28: Administration Team Leader | F28: 44387 | H28: TIVF2024 | I28: TAS | J28: Full Time | K28: 44387 | L28: 44387 | O28: 37.5
A29: 140 | C29: VIC-TAS | D29: Virtus Health | E29: Embryologist | F29: 44481 | H29: TIVF2024 | I29: TAS | J29: Full Time | K29: 44481 | L29: 44481 | O29: 37.5
A30: 141 | C30: VIC-TAS | D30: Virtus Health | E30: Registered Nurse | F30: 11/29/2021 | H30: TIVF2024 | I30: TAS | J30: Casual | K30: 11/29/2021 | L30: 11/29/2021 | O30: 38
A31: 143 | C31: VIC-TAS | D31: Virtus Health | E31: Embryologist | F31: 44866 | H31: TIVF2024 | I31: TAS | J31: Part Time | K31: 44866 | L31: 44866 | O31: 30
A32: 147 | C32: VIC-TAS | D32: Virtus Health | E32: Patient Liaison Administrator | F32: 3/14/2022 | H32: TIVF2024 | I32: TAS | J32: Full Time | K32: 3/14/2022 | L32: 3/14/2022 | O32: 37.5
A33: 148 | C33: VIC-TAS | D33: Virtus Health | E33: Registered Nurse | F33: 3/28/2022 | H33: TIVF2024 | I33: TAS | J33: Part Time | K33: 3/28/2022 | L33: 3/28/2022 | O33: 16
A34: 153 | C34: VIC-TAS | D34: Virtus Health | E34: Registered Nurse | F34: 39295 | H34: MIVFN2023 | I34: VIC | J34: Part Time | K34: 39295 | L34: 39295 | O34: 34.2
A35: 165 | C35: VIC-TAS | D35: Virtus Health | E35: Embryologist | F35: 39359 | H35: MIVFS2022 | I35: VIC | J35: Full Time | K35: 39359 | L35: 39359 | O35: 38
A36: 198 | C36: VIC-TAS | D36: Virtus Health | E36: Genetics Senior Scientist | F36: 39367 | H36: MIVFS2022 | I36: VIC | J36: Part Time | K36: 39367 | L36: 39367 | O36: 22.8
A37: 214 | C37: VIC-TAS | D37: Virtus Health | E37: Genetics Senior Scientist | F37: 39484 | H37: MIVFS2022 | I37: VIC | J37: Full Time | K37: 39484 | L37: 39484 | O37: 38
A38: 235 | C38: VIC-TAS | D38: Virtus Health | E38: Registered Nurse | F38: 8/27/2008 | H38: MIVFN2023 | I38: VIC | J38: Part Time | K38: 8/27/2008 | L38: 8/27/2008 | O38: 22.8
A39: 270 | C39: VIC-TAS | D39: Virtus Health | E39: Clinical Research Associate | F39: 1/19/2009 | H39: MIVFS2022 | I39: VIC | J39: Full Time | K39: 1/19/2009 | L39: 1/19/2009 | O39: 38
A40: 282 | C40: VIC-TAS | D40: Virtus Health | E40: Nurse Unit Manager | F40: 5/18/2009 | H40: MIVFN2023 | I40: VIC | J40: Full Time | K40: 5/18/2009 | L40: 5/18/2009 | O40: 38
A41: 286 | C41: VIC-TAS | D41: Virtus Health | E41: Embryologist | F41: 5/25/2009 | H41: MIVFS2022 | I41: VIC | J41: Full Time | K41: 5/25/2009 | L41: 5/25/2009 | O41: 38
A42: 299 | C42: VIC-TAS | D42: Virtus Health | E42: Clinical Research Manager | F42: 8/24/2009 | H42: MIVFS2022 | I42: VIC | J42: Full Time | K42: 8/24/2009 | L42: 8/24/2009 | O42: 38
A43: 318 | C43: VIC-TAS | D43: Virtus Health | E43: Embryologist | F43: 39855 | H43: MIVFS2022 | I43: VIC | J43: Part Time | K43: 39855 | L43: 39855 | O43: 32
A44: 341 | C44: VIC-TAS | D44: Virtus Health | E44: General Manager - Operations | F44: 4/27/2010 | H44: VIC | I44: VIC | J44: Full Time | K44: 4/27/2010 | L44: 4/27/2010 | O44: 38
A45: 342 | C45: VIC-TAS | D45: Virtus Health | E45: Accounts Receivable Administrator | F45: 4/19/2010 | H45: MIVFS2022 | I45: VIC | J45: Full Time | K45: 4/19/2010 | L45: 4/19/2010 | O45: 38
A46: 368 | C46: VIC-TAS | D46: Virtus Health | E46: CSSD Technician | F46: 40634 | H46: MIVFS2022 | I46: VIC | J46: Full Time | K46: 40634 | L46: 40634 | O46: 38
A47: 406 | C47: VIC-TAS | D47: Virtus Health | E47: Embryologist | F47: 40851 | H47: MIVFS2022 | I47: VIC | J47: Full Time | K47: 40851 | L47: 40851 | O47: 38
A48: 440 | C48: VIC-TAS | D48: Virtus Health | E48: Registered Nurse | F48: 7/27/2011 | H48: MIVFN2023 | I48: VIC | J48: Part Time | K48: 7/27/2011 | L48: 7/27/2011 | O48: 16
A49: 442 | C49: VIC-TAS | D49: Virtus Health | E49: Registered Nurse | F49: 40763 | H49: MIVFN2023 | I49: VIC | J49: Part Time | K49: 40763 | L49: 40763 | O49: 8
A50: 455 | C50: VIC-TAS | D50: Virtus Health | E50: Embryologist | F50: 40886 | H50: MIVFS2022 | I50: VIC | J50: Full Time | K50: 40886 | L50: 40886 | O50: 38
A51: 512 | C51: VIC-TAS | D51: Virtus Health | E51: IVF Laboratory Manager | F51: 40943 | H51: MIVFS2022 | I51: VIC | J51: Full Time | K51: 40943 | L51: 40943 | O51: 38
A52: 521 | C52: VIC-TAS | D52: Virtus Health | E52: Accounts Receivable Administrator | F52: 4/16/2012 | H52: MIVFS2022 | I52: VIC | J52: Full Time | K52: 4/16/2012 | L52: 4/16/2012 | O52: 38
A53: 529 | C53: VIC-TAS | D53: Virtus Health | E53: Registered Nurse | F53: 5/14/2012 | H53: MIVFN2023 | I53: VIC | J53: Casual | K53: 5/14/2012 | L53: 5/14/2012 | O53: 38
A54: 549 | C54: VIC-TAS | D54: Virtus Health | E54: Counsellling Administrator | F54: 6/20/2012 | H54: MIVFS2022 | I54: VIC | J54: Part Time | K54: 6/20/2012 | L54: 6/20/2012 | O54: 34.2
A55: 609 | C55: VIC-TAS | D55: Virtus Health | E55: Receptionist | F55: 8/20/2012 | H55: MIVFS2022 | I55: VIC | J55: Full Time | K55: 8/20/2012 | L55: 8/20/2012 | O55: 38
A56: 700 | C56: VIC-TAS | D56: Virtus Health | E56: Andrologist | F56: 40918 | H56: MIVFS2022 | I56: VIC | J56: Part Time | K56: 40918 | L56: 40918 | O56: 30.4
A57: 721 | C57: VIC-TAS | D57: Virtus Health | E57: Registered Nurse | F57: 1/21/2013 | H57: MIVFN2023 | I57: VIC | J57: Part Time | K57: 1/21/2013 | L57: 1/21/2013 | O57: 26.6
A58: 722 | C58: VIC-TAS | D58: Virtus Health | E58: Accounts Receivable Administrator | F58: 1/24/2013 | H58: MIVFS2022 | I58: VIC | J58: Part Time | K58: 1/24/2013 | L58: 1/24/2013 | O58: 15.2
A59: 725 | C59: VIC-TAS | D59: Virtus Health | E59: Pathalogy Scientist | F59: 2/27/2013 | H59: MIVFS2022 | I59: VIC | J59: Full Time | K59: 2/27/2013 | L59: 2/27/2013 | O59: 38
A60: 726 | C60: VIC-TAS | D60: Virtus Health | E60: Pathology Laboratory Technician | F60: 2/27/2013 | H60: IVFS2023 | I60: VIC | J60: Full Time | K60: 2/27/2013 | L60: 2/27/2013 | O60: 38
A61: 746 | C61: VIC-TAS | D61: Virtus Health | E61: Genetic Counsellor | F61: 5/22/2013 | H61: MIVFC2021 | I61: VIC | J61: Part Time | K61: 5/22/2013 | L61: 5/22/2013 | O61: 15.2
A62: 771 | C62: VIC-TAS | D62: Virtus Health | E62: Patient Liaison Administrator | F62: 8/26/2013 | H62: MIVFS2022 | I62: VIC | J62: Part Time | K62: 8/26/2013 | L62: 8/26/2013 | O62: 22.8
A63: 786 | C63: VIC-TAS | D63: Virtus Health | E63: Registered Nurse | F63: 41589 | H63: MIVFN2023 | I63: VIC | J63: Part Time | K63: 41589 | L63: 41589 | O63: 19
A64: 796 | C64: VIC-TAS | D64: Virtus Health | E64: Embryologist | F64: 41791 | H64: MIVFS2022 | I64: VIC | J64: Part Time | K64: 41791 | L64: 41791 | O64: 30.4
A65: 801 | C65: VIC-TAS | D65: Virtus Health | E65: Counsellor | F65: 1/28/2014 | H65: MIVFC2021 | I65: VIC | J65: Part Time | K65: 1/28/2014 | L65: 1/28/2014 | O65: 30.4
A66: 802 | C66: VIC-TAS | D66: Virtus Health | E66: Counsellor | F66: 1/28/2014 | H66: MIVFC2021 | I66: VIC | J66: Part Time | K66: 1/28/2014 | L66: 1/28/2014 | O66: 15.2
A67: 838 | C67: VIC-TAS | D67: Virtus Health | E67: Andrology Laboratory Manager | F67: 41918 | H67: MIVFS2022 | I67: VIC | J67: Full Time | K67: 41918 | L67: 41918 | O67: 38
A68: 846 | C68: VIC-TAS | D68: Virtus Health | E68: Customer Service Consultant | F68: 41889 | H68: MIVFS2022 | I68: VIC | J68: Full Time | K68: 41889 | L68: 41889 | O68: 38
A69: 857 | C69: VIC-TAS | D69: Virtus Health | E69: Embryologist | F69: 41981 | H69: MIVFS2022 | I69: VIC | J69: Full Time | K69: 41981 | L69: 41981 | O69: 38
A70: 862 | C70: VIC-TAS | D70: Virtus Health | E70: IVF Laboratory Supervisor - Templestowe | F70: 9/15/2014 | H70: MIVFS2022 | I70: VIC | J70: Full Time | K70: 9/15/2014 | L70: 9/15/2014 | O70: 38
A71: 869 | C71: VIC-TAS | D71: Virtus Health | E71: Andrologist | F71: 41861 | H71: MIVFS2022 | I71: VIC | J71: Part Time | K71: 41861 | L71: 41861 | O71: 30.4
A72: 873 | C72: VIC-TAS | D72: Virtus Health | E72: Andrologist | F72: 12/18/2014 | H72: MIVFS2022 | I72: VIC | J72: Part Time | K72: 12/18/2014 | L72: 12/18/2014 | O72: 22.8
A73: 888 | C73: VIC-TAS | D73: Virtus Health | E73: Quality Assurance Embryologist | F73: 42313 | H73: MIVFS2022 | I73: VIC | J73: Full Time | K73: 42313 | L73: 42313 | O73: 38
A74: 901 | C74: VIC-TAS | D74: Virtus Health | E74: Phlebotomist | F74: 10/26/2015 | H74: IVFS2023 | I74: VIC | J74: Part Time | K74: 10/26/2015 | L74: 10/26/2015 | O74: 22.8
A75: 910 | C75: VIC-TAS | D75: Virtus Health | E75: Enrolled Nurse | F75: 11/30/2015 | H75: MIVFN2023 | I75: VIC | J75: Part Time | K75: 11/30/2015 | L75: 11/30/2015 | O75: 29
A76: 913 | C76: VIC-TAS | D76: Virtus Health | E76: Registered Nurse | F76: 42016 | H76: MIVFN2023 | I76: VIC | J76: Full Time | K76: 42016 | L76: 42016 | O76: 38
A77: 917 | C77: VIC-TAS | D77: Virtus Health | E77: Quality Assurance Embryologist | F77: 42676 | H77: MIVFS2022 | I77: VIC | J77: Part Time | K77: 42676 | L77: 42676 | O77: 36
A78: 931 | C78: VIC-TAS | D78: Virtus Health | E78: Clinical Nurse Specialist | F78: 2/22/2016 | H78: MIVFN2023 | I78: VIC | J78: Part Time | K78: 2/22/2016 | L78: 2/22/2016 | O78: 22.5
A79: 932 | C79: VIC-TAS | D79: Virtus Health | E79: Registered Nurse | F79: 3/14/2016 | H79: MIVFN2023 | I79: VIC | J79: Casual | K79: 3/14/2016 | L79: 3/14/2016 | O79: 38
A80: 952 | C80: VIC-TAS | D80: Virtus Health | E80: Associate Nurse Unit Manager | F80: 42681 | H80: MIVFN2023 | I80: VIC | J80: Full Time | K80: 42681 | L80: 42681 | O80: 38
A81: 965 | C81: VIC-TAS | D81: Virtus Health | E81: Genetic Scientist | F81: 10/24/2016 | H81: MIVFS2022 | I81: VIC | J81: Full Time | K81: 10/24/2016 | L81: 10/24/2016 | O81: 38
A82: 983 | C82: VIC-TAS | D82: Virtus Health | E82: Director of Art Services | F82: 42889 | H82: VIC | I82: VIC | J82: Full Time | K82: 42889 | L82: 42889 | O82: 38
A83: 985 | C83: VIC-TAS | D83: Virtus Health | E83: Registered Nurse | F83: 43012 | H83: MIVFN2023 | I83: VIC | J83: Casual | K83: 43012 | L83: 43012 | O83: 38
A84: 993 | C84: VIC-TAS | D84: Virtus Health | E84: Registered Nurse | F84: 6/26/2017 | H84: MIVFN2023 | I84: VIC | J84: Full Time | K84: 6/26/2017 | L84: 6/26/2017 | O84: 38
A85: 994 | C85: VIC-TAS | D85: Virtus Health | E85: Health Information Manager | F85: 43076 | H85: VIC | I85: VIC | J85: Casual | K85: 43076 | L85: 43076 | O85: 38
A86: 1005 | C86: VIC-TAS | D86: Virtus Health | E86: Registered Nurse | F86: 8/28/2017 | H86: MIVFN2023 | I86: VIC | J86: Part Time | K86: 8/28/2017 | L86: 8/28/2017 | O86: 15.2
A87: 1025 | C87: VIC-TAS | D87: Virtus Health | E87: Phlebotomist | F87: 42835 | H87: IVFS2023 | I87: VIC | J87: Part Time | K87: 42835 | L87: 42835 | O87: 11.4
A88: 1027 | C88: VIC-TAS | D88: Virtus Health | E88: Registered Nurse | F88: 11/20/2017 | H88: MIVFN2023 | I88: VIC | J88: Part Time | K88: 11/20/2017 | L88: 11/20/2017 | O88: 15.2
A89: 1032 | C89: VIC-TAS | D89: Virtus Health | E89: IVF Laboratory Team Leader | F89: 42837 | H89: MIVFS2022 | I89: VIC | J89: Full Time | K89: 42837 | L89: 42837 | O89: 38
A90: 1034 | C90: VIC-TAS | D90: Virtus Health | E90: IVF Laboratory Team Leader | F90: 1/22/2018 | H90: MIVFS2022 | I90: VIC | J90: Full Time | K90: 1/22/2018 | L90: 1/22/2018 | O90: 38
A91: 1040 | C91: VIC-TAS | D91: Virtus Health | E91: Counselling Manager | F91: 2/21/2018 | H91: VIC | I91: VIC | J91: Part Time | K91: 2/21/2018 | L91: 2/21/2018 | O91: 30.4
A92: 1043 | C92: VIC-TAS | D92: Virtus Health | E92: Associate Nurse Manager | F92: 3/19/2018 | H92: MIVFN2023 | I92: VIC | J92: Full Time | K92: 3/19/2018 | L92: 3/19/2018 | O92: 38
A93: 1046 | C93: VIC-TAS | D93: Virtus Health | E93: Nurse Educator | F93: 3/19/2018 | H93: MIVFN2023 | I93: VIC | J93: Full Time | K93: 3/19/2018 | L93: 3/19/2018 | O93: 38
A94: 1053 | C94: VIC-TAS | D94: Virtus Health | E94: Counsellor | F94: 43438 | H94: MIVFC2021 | I94: TAS | J94: Part Time | K94: 43438 | L94: 43438 | O94: 22.8
A95: 1068 | C95: VIC-TAS | D95: Virtus Health | E95: Registered Nurse | F95: 6/22/2018 | H95: MIVFN2023 | I95: VIC | J95: Part Time | K95: 6/22/2018 | L95: 6/22/2018 | O95: 19
A96: 1076 | C96: VIC-TAS | D96: Virtus Health | E96: Enrolled Nurse | F96: 7/23/2018 | H96: MIVFN2023 | I96: VIC | J96: Part Time | K96: 7/23/2018 | L96: 7/23/2018 | O96: 15.2
A97: 1080 | C97: VIC-TAS | D97: Virtus Health | E97: Registered Nurse | F97: 8/21/2018 | H97: MIVFN2023 | I97: VIC | J97: Full Time | K97: 8/21/2018 | L97: 8/21/2018 | O97: 38
A98: 1092 | C98: VIC-TAS | D98: Virtus Health | E98: Pathology Scientist | F98: 10/27/2015 | H98: MIVFS2022 | I98: VIC | J98: Full Time | K98: 10/27/2015 | L98: 10/27/2015 | O98: 38
A99: 1096 | C99: VIC-TAS | D99: Virtus Health | E99: Embryologist | F99: 11/26/2018 | H99: MIVFS2022 | I99: VIC | J99: Full Time | K99: 11/26/2018 | L99: 11/26/2018 | O99: 38
A100: 1098 | C100: VIC-TAS | D100: Virtus Health | E100: Enrolled Nurse | F100: 4/29/2014 | H100: MIVFN2023 | I100: VIC | J100: Part Time | K100: 4/29/2014 | L100: 4/29/2014 | O100: 15.2
...

Sheet Sheet3
A1: Code | B1: Date Hired | C1: Job Classification | D1: Column2 | E1: Employment Type | F1: Award Type | G1: Physical State | H1: Normal Hours Paid | I1: Payroll Company | J1: Column1 | K1: Long Service Leave Balance | L1: Long Service Leave Post Prorata Hours | M1: Long Service Leave Post Prorata Date (Last Processed Period End Date) | N1: Long Service Leave Post Entitlement Date | O1: Long Service Leave Post Entitlement Hours | P1: Long Service Leave Taken | Q1: Termination Date
A2: 20 | B2: 41015 | C2: Registered Nurse | E2: CA - Casual | F2: TAS IVF Nurses Enterprise Agreement | G2: Tasmania | I2: TAS IVF PTY LTD | M2: 41015 | N2: 41015
A3: 994 | B3: 42928 | C3: Health Information Manager | E3: CA - Casual | F3: Common Law Employment Contract | G3: Victoria | I3: MELBOURNE IVF | M3: 42928 | N3: 42928
A4: 1140 | B4: 43726 | C4: Registered Nurse | E4: CA - Casual | F4: Melbourne IVF Nurses Enterprise Agreement | G4: Victoria | I4: MELBOURNE IVF | M4: 43726 | N4: 43726
A5: 105 | B5: 43959 | C5: Enrolled Nurse | E5: CA - Casual | F5: TAS IVF Nurses Enterprise Agreement | G5: Tasmania | I5: TAS IVF PTY LTD | M5: 43959 | N5: 43959
A6: 109 | B6: 43991 | C6: Registered Nurse | E6: CA - Casual | F6: TAS IVF Nurses Enterprise Agreement | G6: Tasmania | I6: TAS IVF PTY LTD | M6: 43991 | N6: 43991
A7: 1198 | B7: 44008 | C7: Enrolled Nurse | E7: CA - Casual | F7: Melbourne IVF Nurses Enterprise Agreement | G7: Victoria | I7: MELBOURNE IVF | M7: 44008 | N7: 44008
A8: 115 | B8: 44032 | C8: CSSD Theatre Technician | E8: CA - Casual | F8: TAS IVF Support Services Enterprise Agreement | G8: Tasmania | I8: TAS IVF PTY LTD | M8: 44032 | N8: 44032
A9: 1262 | B9: 44292 | C9: Courier | E9: CA - Casual | F9: Health Professionals and Support Services Award | G9: Victoria | I9: MELBOURNE IVF | M9: 44292 | N9: 44292
A10: 1324 | B10: 44522 | C10: Registered Nurse | E10: CA - Casual | F10: Melbourne IVF Nurses Enterprise Agreement | G10: Victoria | I10: MELBOURNE IVF | M10: 44522 | N10: 44522
A11: 1441 | B11: 44525 | C11: Enrolled Nurse | E11: CA - Casual | F11: Melbourne IVF Nurses Enterprise Agreement | G11: Victoria | I11: MELBOURNE IVF | M11: 44525 | N11: 44525
A12: 141 | B12: 44529 | C12: Registered Nurse | E12: CA - Casual | F12: TAS IVF Nurses Enterprise Agreement | G12: Tasmania | I12: TAS IVF PTY LTD | M12: 44529 | N12: 44529
A13: 1459 | B13: 44648 | C13: Registered Nurse | E13: CA - Casual | F13: Melbourne IVF Nurses Enterprise Agreement | G13: Victoria | I13: MELBOURNE IVF | M13: 44648 | N13: 44648
A14: 529 | B14: 41043 | C14: Registered Nurse | E14: CA - Casual | F14: Melbourne IVF Nurses Enterprise Agreement | G14: Victoria | I14: MELBOURNE IVF | K14: -0.2 | L14: 195.00 | M14: 44695 | N14: 41043 | P14: 195.20
A15: AU22629 | B15: 44821 | C15: Enrolled Nurse | E15: CA - Casual | F15: Melbourne IVF Nurses Enterprise Agreement | G15: Victoria | I15: MELBOURNE IVF | M15: 44821 | N15: 44821
A16: AU22641 | B16: 44890 | C16: Registered Nurse | E16: CA - Casual | F16: TAS IVF Nurses Enterprise Agreement | G16: Tasmania | I16: TAS IVF PTY LTD | M16: 44890 | N16: 44890
A17: AU22686 | B17: 44909 | C17: Registered Nurse | E17: CA - Casual | F17: Melbourne IVF Nurses Enterprise Agreement | G17: Victoria | I17: MELBOURNE IVF | M17: 44909 | N17: 44909
A18: AU22704 | B18: 44935 | C18: Administration Clerk | E18: CA - Casual | F18: Melbourne IVF Support Services Enterprise Agreement | G18: Victoria | I18: MELBOURNE IVF | M18: 44935 | N18: 44935
A19: 932 | B19: 42443 | C19: Registered Nurse | E19: CA - Casual | F19: Melbourne IVF Nurses Enterprise Agreement | G19: Victoria | I19: MELBOURNE IVF | L19: 72.72 | M19: 44990 | N19: 42443 | P19: 72.72
A20: AU22772 | B20: 44991 | C20: Clinical Research Scientist | E20: FP - Full Time Waged | F20: Melbourne IVF Medical Scientists Enterprise Agreement | G20: Victoria | H20: 76.00 | I20: MELBOURNE IVF | K20: 1.08 | L20: 1.08 | M20: 44997 | N20: 44991
A21: AU23015 | B21: 45198 | C21: Enrolled Nurse | E21: CA - Casual | F21: Melbourne IVF Nurses Enterprise Agreement | G21: Victoria | I21: MELBOURNE IVF | K21: 10.35 | L21: 10.35 | M21: 45075 | N21: 45075
A22: AU22898 | B22: 45110 | C22: Registered Nurse | E22: CA - Casual | F22: TAS IVF Nurses Enterprise Agreement | G22: Tasmania | I22: TAS IVF PTY LTD | M22: 45110 | N22: 45110
A23: AU22912 | B23: 45119 | C23: Theatre Technician | E23: CA - Casual | F23: Melbourne IVF Support Services Enterprise Agreement | G23: Victoria | I23: MELBOURNE IVF | M23: 45119 | N23: 45119
A24: AU22934 | B24: 45141 | C24: Registered Nurse | E24: CA - Casual | F24: TAS IVF Nurses Enterprise Agreement | G24: Tasmania | I24: TAS IVF PTY LTD | M24: 45141 | N24: 45141
A25: AU22960 | B25: 45148 | C25: Patient Liaison Administrator | E25: CA - Casual | F25: TAS IVF Support Services Enterprise Agreement | G25: Tasmania | I25: TAS IVF PTY LTD | M25: 45148 | N25: 45148
A26: AU22975 | B26: 45181 | C26: Registered Nurse | E26: CA - Casual | F26: TAS IVF Nurses Enterprise Agreement | G26: Tasmania | I26: TAS IVF PTY LTD | M26: 45181 | N26: 45181
A27: AU22981 | B27: 45191 | C27: Registered Nurse | E27: CA - Casual | F27: TAS IVF Nurses Enterprise Agreement | G27: Tasmania | I27: TAS IVF PTY LTD | M27: 45191 | N27: 45191
A28: AU23008 | B28: 45201 | C28: Theatre Orderly | E28: CA - Casual | F28: TAS IVF Support Services Enterprise Agreement | G28: Tasmania | I28: TAS IVF PTY LTD | M28: 45201 | N28: 45201
A29: AU23004 | B29: 45224 | C29: Enrolled Nurse | E29: CA - Casual | F29: TAS IVF Nurses Enterprise Agreement | G29: Tasmania | I29: TAS IVF PTY LTD | M29: 45224 | N29: 45224
A30: AU23078 | B30: 45273 | C30: General Practitioner | E30: CO - Contract | F30: Common Law Employment Contract | G30: Victoria | H30: 38.00 | I30: MELBOURNE IVF | M30: 45273 | N30: 45273
A31: AU23088 | B31: 45341 | C31: Registered Nurse | E31: CA - Casual | F31: TAS IVF Nurses Enterprise Agreement | G31: Tasmania | I31: TAS IVF PTY LTD | M31: 45341 | N31: 45341
A32: AU23289 | B32: 45509 | C32: Registered Nurse | E32: CA - Casual | F32: TAS IVF Nurses Enterprise Agreement | G32: Tasmania | I32: TAS IVF PTY LTD | M32: 45509 | N32: 45509
A33: AU23344 | B33: 45538 | C33: Project Operation | E33: CA - Casual | F33: Common Law Employment Contract | G33: Victoria | I33: MELBOURNE IVF | M33: 45538 | N33: 45538
A34: AU23353 | B34: 45544 | C34: Phlebotomist | E34: CA - Casual | F34: Health Professionals and Support Services Award | G34: Victoria | I34: MELBOURNE IVF | M34: 45544 | N34: 45544
A35: AU23397 | B35: 45574 | C35: Administration Clerk | E35: CA - Casual | F35: Melbourne IVF Support Services Enterprise Agreement | G35: Victoria | I35: MELBOURNE IVF | M35: 45574 | N35: 45574
A36: AU23409 | B36: 45595 | C36: Registered Nurse | E36: CA - Casual | F36: TAS IVF Nurses Enterprise Agreement | G36: Tasmania | I36: TAS IVF PTY LTD | M36: 45595 | N36: 45595
A37: AU23416 | B37: 45601 | C37: Administration Clerk | E37: CA - Casual | F37: Melbourne IVF Support Services Enterprise Agreement | G37: Victoria | I37: MELBOURNE IVF | M37: 45601 | N37: 45601
A38: AU23463 | B38: 45630 | C38: Theatre Technician | E38: CA - Casual | F38: Melbourne IVF Support Services Enterprise Agreement | G38: Victoria | I38: MELBOURNE IVF | M38: 45630 | N38: 45630
A39: AU23461 | B39: 45635 | C39: Assistant in Nursing | E39: CA - Casual | F39: Common Law Employment Contract | G39: Victoria | I39: MELBOURNE IVF | M39: 45635 | N39: 45635
A40: AU23462 | B40: 45642 | C40: Registered Nurse | E40: CA - Casual | F40: Melbourne IVF Nurses Enterprise Agreement | G40: Victoria | I40: MELBOURNE IVF | M40: 45642 | N40: 45642
A41: AU23475 | B41: 45671 | C41: Theatre Orderly | E41: CA - Casual | F41: TAS IVF Support Services Enterprise Agreement | G41: Tasmania | I41: TAS IVF PTY LTD | M41: 45671 | N41: 45671
A42: AU23529 | B42: 45712 | C42: Registered Nurse | E42: CA - Casual | F42: Melbourne IVF Nurses Enterprise Agreement | G42: Victoria | I42: MELBOURNE IVF | M42: 45712 | N42: 45712
... A45: AU23528 | B45: 45719 | C45: Assistant in Nursing | E45: CA - Casual | F45: Common Law Employment Contract | G45: Victoria | I45: MELBOURNE IVF | M45: 45719 | N45: 45719
A46: 985 | B46: 42835 | C46: Registered Nurse | E46: CA - Casual | F46: Melbourne IVF Nurses Enterprise Agreement | G46: Victoria | I46: MELBOURNE IVF | K46: 178.67 | M46: 45725 | N46: 45725 | O46: 178.67
A47: AU23588 | B47: 45740 | C47: Phlebotomist | E47: CA - Casual | F47: Health Professionals and Support Services Award | G47: Victoria | I47: MELBOURNE IVF | M47: 45740 | N47: 45740
A48: AU23595 | B48: 45740 | C48: Phlebotomist | E48: CA - Casual | F48: Health Professionals and Support Services Award | G48: Victoria | I48: MELBOURNE IVF | M48: 45740 | N48: 45740
A49: AU23634 | B49: 45782 | C49: Counsellor | E49: CA - Casual | F49: Melbourne IVF Counselling Enterprise Agreement | G49: Victoria | I49: MELBOURNE IVF | K49: 72.3 | L49: 88.94 | M49: 45781 | N49: 44799 | O49: 431.76 | P49: 448.40
A50: AU23643 | B50: 45789 | C50: Registered Nurse | E50: CA - Casual | F50: Melbourne IVF Nurses Enterprise Agreement | G50: Victoria | I50: MELBOURNE IVF | M50: 45789 | N50: 45789
A51: AU23645 | B51: 45790 | C51: Registered Nurse | E51: CA - Casual | F51: Melbourne IVF Nurses Enterprise Agreement | G51: Victoria | I51: MELBOURNE IVF | M51: 45790 | N51: 45790
A52: AU23648 | B52: 45796 | C52: Phlebotomist | E52: CA - Casual | F52: Health Professionals and Support Services Award | G52: Victoria | I52: MELBOURNE IVF | M52: 45796 | N52: 45796
A53: AU23649 | B53: 45796 | C53: Administration | E53: CA - Casual | F53: Melbourne IVF Support Services Enterprise Agreement | G53: Victoria | I53: MELBOURNE IVF | M53: 45796 | N53: 45796
A54: AU23650 | B54: 45796 | C54: CSSD Theatre Technician | E54: CA - Casual | F54: TAS IVF Support Services Enterprise Agreement | G54: Tasmania | I54: TAS IVF PTY LTD | M54: 45796 | N54: 45796
A55: AU23664 | B55: 45799 | C55: Receptionist | E55: CA - Casual | F55: Melbourne IVF Medical Scientists Enterprise Agreement | G55: Victoria | I55: MELBOURNE IVF | M55: 45799 | N55: 45799
A56: AU23661 | B56: 45803 | C56: Assistant in Nursing | E56: CA - Casual | F56: Common Law Employment Contract | G56: Victoria | I56: MELBOURNE IVF | M56: 45803 | N56: 45803
A57: AU23666 | B57: 45803 | C57: Administration | E57: CA - Casual | F57: Melbourne IVF Support Services Enterprise Agreement | G57: Victoria | I57: MELBOURNE IVF | M57: 45803 | N57: 45803
A58: AU23659 | B58: 45810 | C58: CSSD Theatre Technician | E58: CA - Casual | F58: TAS IVF Support Services Enterprise Agreement | G58: Tasmania | I58: TAS IVF PTY LTD | M58: 45810 | N58: 45810
A59: AU23705 | B59: 45817 | C59: Administration Clerk | E59: CA - Casual | F59: Melbourne IVF Support Services Enterprise Agreement | G59: Victoria | I59: MELBOURNE IVF | M59: 45817 | N59: 45817
A60: AU23707 | B60: 45833 | C60: Assistant in Nursing | E60: CA - Casual | F60: Common Law Employment Contract | G60: Victoria | I60: MELBOURNE IVF | M60: 45833 | N60: 45833
A61: AU23709 | B61: 45845 | C61: Registered Nurse | E61: CA - Casual | F61: TAS IVF Nurses Enterprise Agreement | G61: Tasmania | I61: TAS IVF PTY LTD | M61: 45845 | N61: 45845
... A66: AU23816 | B66: 45907 | C66: Administration | E66: CA - Casual | F66: Melbourne IVF Support Services Enterprise Agreement | G66: Victoria | I66: MELBOURNE IVF | M66: 45907 | N66: 45124
A67: AU21026 | B67: 37186 | C67: Embryologist | E67: PT - Part Time Waged | F67: Melbourne IVF Medical Scientists Enterprise Agreement | G67: Victoria | H67: 64.00 | I67: MELBOURNE IVF | K67: -0.57 | L67: 219.11 | M67: 45949 | N67: 44491 | O67: 316.32 | P67: 536.00
A68: AU21033 | B68: 37370 | C68: Embryologist | E68: PT - Part Time Waged | F68: Melbourne IVF Medical Scientists Enterprise Agreement | G68: Victoria | H68: 40.00 | I68: MELBOURNE IVF | K68: 71.61 | L68: 121.47 | M68: 45949 | N68: 44675 | O68: 190.14 | P68: 240.00
A69: AU21031 | B69: 37305 | C69: Genetic Laboratory Manager | E69: FP - Full Time Waged | F69: Melbourne IVF Medical Scientists Enterprise Agreement | G69: Victoria | H69: 76.00 | I69: MELBOURNE IVF | K69: 437.25 | L69: 242.56 | M69: 45949 | N69: 44610 | O69: 954.69 | P69: 760.00
A70: AU21035 | B70: 37382 | C70: Head of Department | E70: FP - Full Time Waged | F70: Melbourne IVF Medical Scientists Enterprise Agreement | G70: Victoria | H70: 76.00 | I70: MELBOURNE IVF | K70: 1133.92 | L70: 228.61 | M70: 45949 | N70: 44687 | O70: 1,315.71 | P70: 410.40
A71: AU21005 | B71: 34547 | C71: Embryologist | E71: FP - Full Time Waged | F71: Melbourne IVF Medical Scientists Enterprise Agreement | G71: Victoria | H71: 76.00 | I71: MELBOURNE IVF | K71: 198.53 | L71: 69.96 | M71: 45949 | N71: 45505 | O71: 282.57 | P71: 154.00
A72: AU21025 | B72: 37165 | C72: Accounts Payable Administrator | E72: FP - Full Time Waged | F72: Melbourne IVF Support Services Enterprise Agreement | G72: Victoria | H72: 76.00 | I72: MELBOURNE IVF | K72: 1511.18 | L72: 267.92 | M72: 45949 | N72: 44470 | O72: 1,243.26
A73: AU21019 | B73: 36913 | C73: Associate Nurse Unit Manager | E73: PT - Part Time Waged | F73: Melbourne IVF Nurses Enterprise Agreement | G73: Victoria | H73: 30.40 | I73: MELBOURNE IVF | K73: 577.59 | L73: 126.66 | M73: 45949 | N73: 44218 | O73: 526.93 | P73: 76.00
A74: 124 | B74: 38740 | C74: Embryologist | E74: PT - Part Time Waged | F74: Melbourne IVF Medical Scientists Enterprise Agreement | G74: Victoria | H74: 64.00 | I74: MELBOURNE IVF | K74: 395.18 | L74: 263.91 | M74: 45949 | N74: 44219 | O74: 539.27 | P74: 408.00
A75: 153 | B75: 39090 | C75: Registered Nurse | E75: PT - Part Time Waged | F75: Melbourne IVF Nurses Enterprise Agreement | G75: Victoria | H75: 68.40 | I75: MELBOURNE IVF | K75: 426.79 | L75: 93.62 | M75: 45949 | N75: 44569 | O75: 652.37 | P75: 319.20
A76: 165 | B76: 39182 | C76: Embryologist | E76: FP - Full Time Waged | F76: Melbourne IVF Medical Scientists Enterprise Agreement | G76: Victoria | H76: 76.00 | I76: MELBOURNE IVF | K76: 617.04 | L76: 233.32 | M76: 45949 | N76: 44661 | O76: 461.72 | P76: 78.00
A77: 198 | B77: 39426 | C77: Genetics Senior Scientist | E77: PT - Part Time Waged | F77: Melbourne IVF Medical Scientists Enterprise Agreement | G77: Victoria | H77: 45.60 | I77: MELBOURNE IVF | K77: 178.67 | L77: 162.75 | M77: 45949 | N77: 44905 | O77: 973.52 | P77: 957.60
A78: 214 | B78: 39601 | C78: Genetics Senior Scientist | E78: FP - Full Time Waged | F78: Melbourne IVF Medical Scientists Enterprise Agreement | G78: Victoria | H78: 76.00 | I78: MELBOURNE IVF | K78: 1111.94 | L78: 157.60 | M78: 45949 | N78: 45079 | O78: 954.34
A79: 235 | B79: 39687 | C79: Registered Nurse | E79: PT - Part Time Waged | F79: Melbourne IVF Nurses Enterprise Agreement | G79: Victoria | H79: 45.60 | I79: MELBOURNE IVF | K79: 496.59 | L79: 108.55 | M79: 45949 | N79: 45165 | O79: 494.44 | P79: 106.40
A80: 270 | B80: 39832 | C80: Clinical Research Associate | E80: FP - Full Time Waged | F80: Melbourne IVF Medical Scientists Enterprise Agreement | G80: Victoria | H80: 76.00 | I80: MELBOURNE IVF | K80: 1104.3 | L80: 115.76 | M80: 45949 | N80: 45310 | O80: 988.54
A81: 282 | B81: 39951 | C81: Nurse Unit Manager | E81: FP - Full Time Waged | F81: Melbourne IVF Nurses Enterprise Agreement | G81: Victoria | H81: 76.00 | I81: MELBOURNE IVF | K81: 408.6 | L81: 48.26 | M81: 45949 | N81: 45430 | O81: 360.34
A82: 286 | B82: 39958 | C82: Embryologist | E82: FP - Full Time Waged | F82: Melbourne IVF Medical Scientists Enterprise Agreement | G82: Victoria | H82: 76.00 | I82: MELBOURNE IVF | K82: 605.47 | L82: 92.75 | M82: 45949 | N82: 45437 | O82: 512.72
A83: 299 | B83: 40049 | C83: Clinical Research Manager | E83: FP - Full Time Waged | F83: Melbourne IVF Medical Scientists Enterprise Agreement | G83: Victoria | H83: 76.00 | I83: MELBOURNE IVF | K83: 1064.98 | L83: 76.26 | M83: 45949 | N83: 45528 | O83: 988.72
A84: 318 | B84: 40119 | C84: Embryologist | E84: PT - Part Time Waged | F84: Melbourne IVF Medical Scientists Enterprise Agreement | G84: Victoria | H84: 64.00 | I84: MELBOURNE IVF | K84: 790.15 | L84: 53.54 | M84: 45949 | N84: 45598 | O84: 832.61 | P84: 96.00
A85: 341 | B85: 40295 | C85: General Manager - Operations | E85: FP - Full Time Salaried | F85: Common Law Employment Contract | G85: Victoria | H85: 76.00 | I85: MELBOURNE IVF | K85: 775.54 | L85: 320.02 | M85: 45949 | N85: 43948 | O85: 455.52
A86: 342 | B86: 40287 | C86: Accounts Receivable Administrator | E86: FP - Full Time Waged | F86: Melbourne IVF Support Services Enterprise Agreement | G86: Victoria | H86: 76.00 | I86: MELBOURNE IVF | K86: 119.28 | L86: 353.80 | M86: 45949 | N86: 43933 | O86: 648.98 | P86: 883.50
A87: 368 | B87: 40547 | C87: CSSD Technician | E87: FP - Full Time Waged | F87: Melbourne IVF Support Services Enterprise Agreement | G87: Victoria | H87: 76.00 | I87: MELBOURNE IVF | K87: 974.83 | L87: 974.83 | M87: 45949 | N87: 40547
A88: 406 | B88: 40644 | C88: Embryologist | E88: FP - Full Time Waged | F88: Melbourne IVF Medical Scientists Enterprise Agreement | G88: Victoria | H88: 76.00 | I88: MELBOURNE IVF | K88: 660.92 | L88: 957.32 | M88: 45949 | N88: 40644 | P88: 296.40
A89: 440 | B89: 40751 | C89: Registered Nurse | E89: PT - Part Time Waged | F89: Melbourne IVF Nurses Enterprise Agreement | G89: Victoria | H89: 32.00 | I89: MELBOURNE IVF | K89: 146.15 | L89: 242.15 | M89: 45949 | N89: 40751 | P89: 96.00
A90: 442 | B90: 40763 | C90: Registered Nurse | E90: PT - Part Time Waged | F90: Melbourne IVF Nurses Enterprise Agreement | G90: Victoria | H90: 16.00 | I90: MELBOURNE IVF | K90: 93.02 | L90: 197.02 | M90: 45949 | N90: 40763 | P90: 104.00
A91: 455 | B91: 40798 | C91: Embryologist | E91: FP - Full Time Waged | F91: Melbourne IVF Medical Scientists Enterprise Agreement | G91: Victoria | H91: 76.00 | I91: MELBOURNE IVF | K91: 625.97 | L91: 40.42 | M91: 45949 | N91: 45725 | O91: 891.55 | P91: 306.00
A92: 512 | B92: 41001 | C92: IVF Laboratory Manager | E92: FP - Full Time Waged | F92: Melbourne IVF Medical Scientists Enterprise Agreement | G92: Victoria | H92: 76.00 | I92: MELBOURNE IVF | K92: 509 | L92: 621.00 | M92: 45949 | N92: 41001 | P92: 112.00
A93: 521 | B93: 41015 | C93: Accounts Receivable Administrator | E93: FP - Full Time Waged | F93: Melbourne IVF Support Services Enterprise Agreement | G93: Victoria | H93: 76.00 | I93: MELBOURNE IVF | K93: 890.37 | L93: 890.37 | M93: 45949 | N93: 41015
A94: 549 | B94: 41080 | C94: Counsellling Administrator | E94: PT - Part Time Waged | F94: Melbourne IVF Support Services Enterprise Agreement | G94: Victoria | H94: 68.40 | I94: MELBOURNE IVF | K94: 790.78 | L94: 790.78 | M94: 45949 | N94: 41080
A95: 609 | B95: 41141 | C95: Receptionist | E95: FP - Full Time Waged | F95: Melbourne IVF Support Services Enterprise Agreement | G95: Victoria | H95: 76.00 | I95: MELBOURNE IVF | K95: 373.64 | L95: 867.64 | M95: 45949 | N95: 41141 | P95: 494.00
A96: 700 | B96: 41183 | C96: Andrologist | E96: PT - Part Time Waged | F96: Melbourne IVF Medical Scientists Enterprise Agreement | G96: Victoria | H96: 60.80 | I96: MELBOURNE IVF | K96: 490.16 | L96: 490.16 | M96: 45949 | N96: 41183
A97: 721 | B97: 41295 | C97: Registered Nurse | E97: PT - Part Time Waged | F97: Melbourne IVF Nurses Enterprise Agreement | G97: Victoria | H97: 53.20 | I97: MELBOURNE IVF | K97: 444.28 | L97: 444.28 | M97: 45949 | N97: 41295
A98: 722 | B98: 41298 | C98: Accounts Receivable Administrator | E98: PT - Part Time Waged | F98: Melbourne IVF Support Services Enterprise Agreement | G98: Victoria | H98: 30.40 | I98: MELBOURNE IVF | K98: 337.97 | L98: 337.97 | M98: 45949 | N98: 41298
A99: 725 | B99: 41332 | C99: Pathalogy Scientist | E99: FP - Full Time Waged | F99: Melbourne IVF Medical Scientists Enterprise Agreement | G99: Victoria | H99: 76.00 | I99: MELBOURNE IVF | K99: 506.37 | L99: 833.17 | M99: 45949 | N99: 41332 | P99: 326.80
A100: 726 | B100: 41332 | C100: Pathology Laboratory Technician | E100: FP - Full Time Waged | F100: Health Professionals and Support Services Award | G100: Victoria | H100: 76.00 | I100: MELBOURNE IVF | K100: 574.77 | L100: 833.17 | M100: 45949 | N100: 41332 | P100: 258.40
A101: 746 | B101: 41416 | C101: Genetic Counsellor | E101: PT - Part Time Waged | F101: Melbourne IVF Counselling Enterprise Agreement | G101: Victoria | H101: 30.40 | I101: MELBOURNE IVF | K101: 128.84 | L101: 276.48 | M101: 45949 | N101: 41416 | P101: 147.64
A102: 771 | B102: 41512 | C102: Patient Liaison Administrator | E102: PT - Part Time Waged | F102: Melbourne IVF Support Services Enterprise Agreement | G102: Victoria | H102: 45.60 | I102: MELBOURNE IVF | K102: 313.89 | L102: 83.37 | M102: 45949 | N102: 45164 | O102: 390.12 | P102: 159.60
A103: 786 | B103: 41589 | C103: Registered Nurse | E103: PT - Part Time Waged | F103: Melbourne IVF Nurses Enterprise Agreement | G103: Victoria | H103: 38.00 | I103: MELBOURNE IVF | K103: 311.53 | L103: 52.74 | M103: 45949 | N103: 45249 | O103: 258.79
A104: 796 | B104: 41645 | C104: Embryologist | E104: PT - Part Time Waged | F104: Melbourne IVF Medical Scientists Enterprise Agreement | G104: Victoria | H104: 60.80 | I104: MELBOURNE IVF | K104: 621.35 | L104: 621.35 | M104: 45949 | N104: 41645
A105: 801 | B105: 41667 | C105: Counsellor | E105: PT - Part Time Waged | F105: Melbourne IVF Counselling Enterprise Agreement | G105: Victoria | H105: 60.80 | I105: MELBOURNE IVF | K105: 181.17 | L105: 618.17 | M105: 45949 | N105: 41645 | P105: 437.00
A106: 802 | B106: 41667 | C106: Counsellor | E106: PT - Part Time Waged | F106: Melbourne IVF Counselling Enterprise Agreement | G106: Victoria | H106: 30.40 | I106: MELBOURNE IVF | K106: 299.08 | L106: 344.68 | M106: 45949 | N106: 41667 | P106: 45.60
...
